MANIFEST.in
README.md
setup.py
clickatell/__init__.py
clickatell/exception.py
clickatell.egg-info/PKG-INFO
clickatell.egg-info/SOURCES.txt
clickatell.egg-info/dependency_links.txt
clickatell.egg-info/requires.txt
clickatell.egg-info/top_level.txt
clickatell/http/__init__.py
clickatell/rest/__init__.py
test/test_transport.py