Metadata-Version: 1.0
Name: clickatell
Version: 0.1.2
Summary: Library for interacting with the Clickatell SMS Gateway
Home-page: https://github.com/arcturial/clickatell-python
Author: Chris Brand
Author-email: webmaster@cainsvault.com
License: LICENSE
Keywords: clickatell,sms
Platform: UNKNOWN
